{
    "name": "App\\Repositories\\FolderRepository",
    "line": 7,
    "short_desc": "",
    "long_desc": "",
    "hint": null,
    "tags": [],
    "namespace": "App\\Repositories",
    "file": "\/Users\/akecel\/Development\/0 - Web Project\/Server\/hyra-php-backoffice\/app\/Repositories\/FolderRepository.php",
    "relative_file": null,
    "hash": "37516f653b56893395215f304c19460cc3f44118",
    "parent": "App\\Repositories\\ResourceRepository",
    "modifiers": 0,
    "is_trait": false,
    "is_interface": false,
    "aliases": {
        "Folder": "App\\Models\\Folder"
    },
    "errors": [],
    "interfaces": [],
    "traits": [],
    "properties": [],
    "methods": {
        "__construct": {
            "name": "__construct",
            "line": 10,
            "short_desc": "",
            "long_desc": "",
            "hint": null,
            "hint_desc": null,
            "tags": [],
            "modifiers": 1,
            "is_by_ref": "",
            "exceptions": [],
            "errors": [],
            "parameters": {
                "folder": {
                    "name": "folder",
                    "line": 10,
                    "short_desc": null,
                    "long_desc": null,
                    "hint": [
                        [
                            "\\App\\Models\\Folder",
                            false
                        ]
                    ],
                    "tags": [],
                    "modifiers": {
                        "nodeType": "Name_FullyQualified",
                        "parts": [
                            "App",
                            "Models",
                            "Folder"
                        ],
                        "attributes": {
                            "startLine": 10,
                            "endLine": 10
                        }
                    },
                    "default": null,
                    "variadic": false,
                    "is_by_ref": false
                }
            }
        },
        "getByIdWithFiles": {
            "name": "getByIdWithFiles",
            "line": 15,
            "short_desc": "",
            "long_desc": "",
            "hint": null,
            "hint_desc": null,
            "tags": [],
            "modifiers": 1,
            "is_by_ref": "",
            "exceptions": [],
            "errors": [],
            "parameters": {
                "id": {
                    "name": "id",
                    "line": 15,
                    "short_desc": null,
                    "long_desc": null,
                    "hint": null,
                    "tags": [],
                    "modifiers": null,
                    "default": null,
                    "variadic": false,
                    "is_by_ref": false
                }
            }
        }
    },
    "constants": []
}